merge_args.py
merge_args-0.1.5.dist-info/AUTHORS
merge_args-0.1.5.dist-info/LICENSE
merge_args-0.1.5.dist-info/METADATA
merge_args-0.1.5.dist-info/WHEEL
merge_args-0.1.5.dist-info/top_level.txt
merge_args-0.1.5.dist-info/RECORD
