Metadata-Version: 2.1
Name: merge_args
Version: 0.1.5
Summary: Merge signatures of two functions with Advanced Hackery.
Home-page: https://github.com/Kwpolska/merge_args
Author: Chris Warrick
Author-email: chris@chriswarrick.com
License: 3-clause BSD
Keywords: merge_args
Platform: any
Classifier: Development Status :: 1 - Planning
Classifier: Programming Language :: Python
Classifier: Programming Language :: Python :: 3
Classifier: Programming Language :: Python :: 3.7
Classifier: Programming Language :: Python :: 3.8
Classifier: Programming Language :: Python :: 3.8
Classifier: Programming Language :: Python :: 3.9
Classifier: Programming Language :: Python :: 3.10
Classifier: Programming Language :: Python :: 3.11
License-File: LICENSE
License-File: AUTHORS
